setup.py
far_far_server_messenger.egg-info/PKG-INFO
far_far_server_messenger.egg-info/SOURCES.txt
far_far_server_messenger.egg-info/dependency_links.txt
far_far_server_messenger.egg-info/requires.txt
far_far_server_messenger.egg-info/top_level.txt
server/__init__.py
server/server.py
server/common/__init__.py
server/common/decos.py
server/common/descriptors.py
server/common/errors.py
server/common/functions.py
server/common/metas.py
server/common/vars.py
server/doc/__init__.py
server/doc/source/__init__.py
server/doc/source/conf.py
server/log/__init__.py
server/log/config/__init__.py
server/log/config/client_log_config.py
server/log/config/server_log_config.py
server/server/__init__.py
server/server/add_user.py
server/server/config_window.py
server/server/main_window.py
server/server/remove_user.py
server/server/server_core.py
server/server/server_database.py
server/server/stat_window.py
server/test_dir/__init__.py
server/test_dir/test_client.py
server/test_dir/test_functions.py
server/test_dir/test_server.py