Metadata-Version: 1.0
Name: far-far-server-messenger
Version: 0.0.1
Summary: far_far_messenger
Home-page: UNKNOWN
Author: Fedor Polyakov
Author-email: fp@yandex.ru
License: UNKNOWN
Platform: UNKNOWN
